{
  "last_run": "2026-07-03",
  "failure_counts": {
    "FFIC": {
      "count": 4,
      "first_flagged": "2026-06-26",
      "reason": "No recent data from Yahoo Finance (possibly delisted)"
    },
    "CVGW": {
      "count": 6,
      "first_flagged": "2026-06-18",
      "reason": "No recent data from Yahoo Finance (possibly delisted)"
    },
    "THR": {
      "count": 5,
      "first_flagged": "2026-06-19",
      "reason": "No recent data from Yahoo Finance (possibly delisted)"
    },
    "AMWD": {
      "count": 6,
      "first_flagged": "2026-06-18",
      "reason": "No recent data from Yahoo Finance (possibly delisted)"
    },
    "VSCO": {
      "count": 4,
      "first_flagged": "2026-06-26",
      "reason": "No recent data from Yahoo Finance (possibly delisted)"
    },
    "SCVL": {
      "count": 3,
      "first_flagged": "2026-06-30",
      "reason": "Data stopped updating (last: 2026-06-04, expected: 2026-07-02)"
    },
    "KALV": {
      "count": 3,
      "first_flagged": "2026-06-30",
      "reason": "Data stopped updating (last: 2026-06-04, expected: 2026-07-02)"
    },
    "LC": {
      "count": 2,
      "first_flagged": "2026-07-02",
      "reason": "Data stopped updating (last: 2026-06-18, expected: 2026-07-02)"
    },
    "KW": {
      "count": 3,
      "first_flagged": "2026-06-30",
      "reason": "Data stopped updating (last: 2026-06-15, expected: 2026-07-02)"
    },
    "CWAN": {
      "count": 1,
      "first_flagged": "2026-07-03",
      "reason": "Data stopped updating (last: 2026-06-22, expected: 2026-07-02)"
    },
    "SATS": {
      "count": 1,
      "first_flagged": "2026-07-03",
      "reason": "Data stopped updating (last: 2026-06-22, expected: 2026-07-02)"
    },
    "GPRO": {
      "count": 4,
      "first_flagged": "2026-04-20",
      "reason": "Penny stock ($0.72 < $1.00)"
    },
    "QSI": {
      "count": 7,
      "first_flagged": "2026-03-23",
      "reason": "Penny stock ($0.93 < $1.00)"
    },
    "IVVD": {
      "count": 7,
      "first_flagged": "2026-06-16",
      "reason": "Penny stock ($0.89 < $1.00)"
    },
    "SES": {
      "count": 3,
      "first_flagged": "2026-04-10",
      "reason": "Penny stock ($0.88 < $1.00)"
    },
    "HUMA": {
      "count": 4,
      "first_flagged": "2026-04-20",
      "reason": "Penny stock ($0.71 < $1.00)"
    },
    "SNBR": {
      "count": 3,
      "first_flagged": "2026-06-30",
      "reason": "Penny stock ($0.12 < $1.00)"
    },
    "CGC": {
      "count": 0,
      "first_flagged": "2026-04-08",
      "reason": "Recovered"
    },
    "PROP": {
      "count": 0,
      "first_flagged": "2026-06-16",
      "reason": "Recovered"
    },
    "SLND": {
      "count": 0,
      "first_flagged": "2026-03-23",
      "reason": "Recovered"
    },
    "FLUX": {
      "count": 0,
      "first_flagged": "2026-06-16",
      "reason": "Recovered"
    },
    "GOCO": {
      "count": 0,
      "first_flagged": "2026-06-16",
      "reason": "Recovered"
    },
    "FBLG": {
      "count": 0,
      "first_flagged": "2026-03-30",
      "reason": "Recovered"
    },
    "DH": {
      "count": 0,
      "first_flagged": "2026-06-16",
      "reason": "Recovered"
    },
    "TCRX": {
      "count": 0,
      "first_flagged": "2026-06-16",
      "reason": "Recovered"
    },
    "SEE": {
      "count": 0,
      "first_flagged": "2026-04-17",
      "reason": "Recovered"
    },
    "SPNS": {
      "count": 0,
      "first_flagged": "2026-06-16",
      "reason": "Recovered"
    },
    "LGTY": {
      "count": 0,
      "first_flagged": "2026-04-14",
      "reason": "Recovered"
    },
    "IAS": {
      "count": 0,
      "first_flagged": "2026-06-05",
      "reason": "Recovered"
    },
    "OB": {
      "count": 0,
      "first_flagged": "2026-06-16",
      "reason": "Recovered"
    },
    "BASE": {
      "count": 0,
      "first_flagged": "2026-06-16",
      "reason": "Recovered"
    },
    "KLG": {
      "count": 0,
      "first_flagged": "2026-06-16",
      "reason": "Recovered"
    },
    "BLFY": {
      "count": 0,
      "first_flagged": "2026-06-16",
      "reason": "Recovered"
    },
    "VBTX": {
      "count": 0,
      "first_flagged": "2026-06-16",
      "reason": "Recovered"
    },
    "JNPR": {
      "count": 0,
      "first_flagged": "2026-06-16",
      "reason": "Recovered"
    },
    "VTLE": {
      "count": 0,
      "first_flagged": "2026-06-16",
      "reason": "Recovered"
    },
    "FLIC": {
      "count": 0,
      "first_flagged": "2026-06-16",
      "reason": "Recovered"
    },
    "SRDX": {
      "count": 0,
      "first_flagged": "2026-06-16",
      "reason": "Recovered"
    },
    "HOUS": {
      "count": 0,
      "first_flagged": "2026-06-16",
      "reason": "Recovered"
    },
    "APLT": {
      "count": 0,
      "first_flagged": "2026-06-16",
      "reason": "Recovered"
    },
    "HSII": {
      "count": 0,
      "first_flagged": "2026-06-16",
      "reason": "Recovered"
    },
    "SWKH": {
      "count": 0,
      "first_flagged": "2026-06-05",
      "reason": "Recovered"
    },
    "ADVM": {
      "count": 0,
      "first_flagged": "2026-06-16",
      "reason": "Recovered"
    },
    "NYMT": {
      "count": 0,
      "first_flagged": "2026-06-16",
      "reason": "Recovered"
    },
    "COOP": {
      "count": 0,
      "first_flagged": "2026-06-16",
      "reason": "Recovered"
    },
    "BRKL": {
      "count": 0,
      "first_flagged": "2026-06-16",
      "reason": "Recovered"
    },
    "AGS": {
      "count": 0,
      "first_flagged": "2026-06-16",
      "reason": "Recovered"
    },
    "GPS": {
      "count": 0,
      "first_flagged": "2026-06-16",
      "reason": "Recovered"
    },
    "DESP": {
      "count": 0,
      "first_flagged": "2026-06-16",
      "reason": "Recovered"
    },
    "THRD": {
      "count": 0,
      "first_flagged": "2026-06-16",
      "reason": "Recovered"
    },
    "VCSA": {
      "count": 0,
      "first_flagged": "2026-06-16",
      "reason": "Recovered"
    },
    "VMEO": {
      "count": 0,
      "first_flagged": "2026-06-16",
      "reason": "Recovered"
    },
    "ACCD": {
      "count": 0,
      "first_flagged": "2026-06-16",
      "reason": "Recovered"
    },
    "WOW": {
      "count": 0,
      "first_flagged": "2026-06-16",
      "reason": "Recovered"
    },
    "VRNT": {
      "count": 0,
      "first_flagged": "2026-06-05",
      "reason": "Recovered"
    },
    "ZEUS": {
      "count": 0,
      "first_flagged": "2026-06-16",
      "reason": "Recovered"
    },
    "MRO": {
      "count": 0,
      "first_flagged": "2026-06-16",
      "reason": "Recovered"
    },
    "SHYF": {
      "count": 0,
      "first_flagged": "2026-06-16",
      "reason": "Recovered"
    },
    "RAPT": {
      "count": 0,
      "first_flagged": "2026-06-16",
      "reason": "Recovered"
    },
    "PGRE": {
      "count": 0,
      "first_flagged": "2026-06-16",
      "reason": "Recovered"
    },
    "ANSS": {
      "count": 0,
      "first_flagged": "2026-06-16",
      "reason": "Recovered"
    },
    "EVRI": {
      "count": 0,
      "first_flagged": "2026-06-16",
      "reason": "Recovered"
    },
    "HLVX": {
      "count": 0,
      "first_flagged": "2026-06-16",
      "reason": "Recovered"
    },
    "FI": {
      "count": 0,
      "first_flagged": "2026-06-16",
      "reason": "Recovered"
    },
    "PBPB": {
      "count": 0,
      "first_flagged": "2026-06-16",
      "reason": "Recovered"
    },
    "TEF": {
      "count": 0,
      "first_flagged": "2026-06-16",
      "reason": "Recovered"
    },
    "WBA": {
      "count": 0,
      "first_flagged": "2026-06-16",
      "reason": "Recovered"
    },
    "FARO": {
      "count": 0,
      "first_flagged": "2026-06-16",
      "reason": "Recovered"
    },
    "THS": {
      "count": 0,
      "first_flagged": "2026-06-16",
      "reason": "Recovered"
    },
    "FRGE": {
      "count": 0,
      "first_flagged": "2026-06-16",
      "reason": "Recovered"
    },
    "INZY": {
      "count": 0,
      "first_flagged": "2026-06-16",
      "reason": "Recovered"
    },
    "ALE": {
      "count": 0,
      "first_flagged": "2026-06-16",
      "reason": "Recovered"
    },
    "ALEX": {
      "count": 0,
      "first_flagged": "2026-06-16",
      "reason": "Recovered"
    },
    "BYON": {
      "count": 0,
      "first_flagged": "2026-06-16",
      "reason": "Recovered"
    },
    "CRGX": {
      "count": 0,
      "first_flagged": "2026-06-16",
      "reason": "Recovered"
    },
    "AMRK": {
      "count": 0,
      "first_flagged": "2026-06-16",
      "reason": "Recovered"
    },
    "CSWI": {
      "count": 0,
      "first_flagged": "2026-06-16",
      "reason": "Recovered"
    },
    "IGT": {
      "count": 0,
      "first_flagged": "2026-06-16",
      "reason": "Recovered"
    },
    "AMPS": {
      "count": 0,
      "first_flagged": "2026-06-16",
      "reason": "Recovered"
    },
    "TRML": {
      "count": 0,
      "first_flagged": "2026-06-16",
      "reason": "Recovered"
    },
    "PXD": {
      "count": 0,
      "first_flagged": "2026-06-16",
      "reason": "Recovered"
    },
    "HOLX": {
      "count": 0,
      "first_flagged": "2026-04-14",
      "reason": "Recovered"
    },
    "MODG": {
      "count": 0,
      "first_flagged": "2026-06-16",
      "reason": "Recovered"
    },
    "FNA": {
      "count": 0,
      "first_flagged": "2026-06-16",
      "reason": "Recovered"
    },
    "MLNK": {
      "count": 0,
      "first_flagged": "2026-06-16",
      "reason": "Recovered"
    },
    "STR": {
      "count": 0,
      "first_flagged": "2026-06-16",
      "reason": "Recovered"
    },
    "K": {
      "count": 0,
      "first_flagged": "2026-06-16",
      "reason": "Recovered"
    },
    "VTYX": {
      "count": 0,
      "first_flagged": "2026-06-16",
      "reason": "Recovered"
    },
    "KAR": {
      "count": 0,
      "first_flagged": "2026-06-16",
      "reason": "Recovered"
    },
    "VERV": {
      "count": 0,
      "first_flagged": "2026-06-16",
      "reason": "Recovered"
    },
    "ML": {
      "count": 0,
      "first_flagged": "2026-06-16",
      "reason": "Recovered"
    },
    "SWTX": {
      "count": 0,
      "first_flagged": "2026-06-16",
      "reason": "Recovered"
    },
    "ZIMV": {
      "count": 0,
      "first_flagged": "2026-06-16",
      "reason": "Recovered"
    },
    "SCPH": {
      "count": 0,
      "first_flagged": "2026-06-16",
      "reason": "Recovered"
    },
    "SBT": {
      "count": 0,
      "first_flagged": "2026-06-16",
      "reason": "Recovered"
    },
    "ONTF": {
      "count": 0,
      "first_flagged": "2026-06-16",
      "reason": "Recovered"
    },
    "BPMC": {
      "count": 0,
      "first_flagged": "2026-06-16",
      "reason": "Recovered"
    },
    "MOFG": {
      "count": 0,
      "first_flagged": "2026-06-16",
      "reason": "Recovered"
    },
    "GBIO": {
      "count": 0,
      "first_flagged": "2026-06-16",
      "reason": "Recovered"
    },
    "PVBC": {
      "count": 0,
      "first_flagged": "2026-06-16",
      "reason": "Recovered"
    },
    "MTSR": {
      "count": 0,
      "first_flagged": "2026-06-16",
      "reason": "Recovered"
    },
    "AVTE": {
      "count": 0,
      "first_flagged": "2026-06-16",
      "reason": "Recovered"
    },
    "RDUS": {
      "count": 0,
      "first_flagged": "2026-06-16",
      "reason": "Recovered"
    },
    "SFYX": {
      "count": 0,
      "first_flagged": "2026-06-05",
      "reason": "Recovered"
    },
    "ATSG": {
      "count": 0,
      "first_flagged": "2026-06-16",
      "reason": "Recovered"
    },
    "AKYA": {
      "count": 0,
      "first_flagged": "2026-06-16",
      "reason": "Recovered"
    },
    "TGNA": {
      "count": 0,
      "first_flagged": "2026-06-16",
      "reason": "Recovered"
    },
    "VVPR": {
      "count": 0,
      "first_flagged": "2026-06-16",
      "reason": "Recovered"
    },
    "YMAB": {
      "count": 0,
      "first_flagged": "2026-06-16",
      "reason": "Recovered"
    },
    "HEES": {
      "count": 0,
      "first_flagged": "2026-06-16",
      "reason": "Recovered"
    },
    "IGMS": {
      "count": 0,
      "first_flagged": "2026-06-16",
      "reason": "Recovered"
    },
    "RMBL": {
      "count": 0,
      "first_flagged": "2026-06-16",
      "reason": "Recovered"
    },
    "DENN": {
      "count": 0,
      "first_flagged": "2026-06-16",
      "reason": "Recovered"
    },
    "ETNB": {
      "count": 0,
      "first_flagged": "2026-06-16",
      "reason": "Recovered"
    },
    "MCW": {
      "count": 0,
      "first_flagged": "2026-06-05",
      "reason": "Recovered"
    },
    "RYI": {
      "count": 0,
      "first_flagged": "2026-06-16",
      "reason": "Recovered"
    },
    "AKRO": {
      "count": 0,
      "first_flagged": "2026-06-16",
      "reason": "Recovered"
    },
    "BHLB": {
      "count": 0,
      "first_flagged": "2026-06-16",
      "reason": "Recovered"
    },
    "SSBK": {
      "count": 0,
      "first_flagged": "2026-06-16",
      "reason": "Recovered"
    },
    "AVDX": {
      "count": 0,
      "first_flagged": "2026-06-16",
      "reason": "Recovered"
    },
    "TRUE": {
      "count": 0,
      "first_flagged": "2026-06-16",
      "reason": "Recovered"
    },
    "COMM": {
      "count": 0,
      "first_flagged": "2026-06-16",
      "reason": "Recovered"
    },
    "HBI": {
      "count": 0,
      "first_flagged": "2026-06-16",
      "reason": "Recovered"
    },
    "GMS": {
      "count": 0,
      "first_flagged": "2026-06-16",
      "reason": "Recovered"
    },
    "HI": {
      "count": 0,
      "first_flagged": "2026-06-16",
      "reason": "Recovered"
    },
    "FFNW": {
      "count": 0,
      "first_flagged": "2026-06-16",
      "reason": "Recovered"
    },
    "GLDD": {
      "count": 0,
      "first_flagged": "2026-06-16",
      "reason": "Recovered"
    },
    "DVAX": {
      "count": 0,
      "first_flagged": "2026-06-16",
      "reason": "Recovered"
    },
    "SMLR": {
      "count": 0,
      "first_flagged": "2026-06-16",
      "reason": "Recovered"
    },
    "ATXS": {
      "count": 0,
      "first_flagged": "2026-06-16",
      "reason": "Recovered"
    },
    "IRBT": {
      "count": 0,
      "first_flagged": "2026-06-16",
      "reason": "Recovered"
    },
    "BLDE": {
      "count": 0,
      "first_flagged": "2026-06-16",
      "reason": "Recovered"
    },
    "ENFN": {
      "count": 0,
      "first_flagged": "2026-06-16",
      "reason": "Recovered"
    },
    "ETWO": {
      "count": 0,
      "first_flagged": "2026-06-16",
      "reason": "Recovered"
    },
    "IPG": {
      "count": 0,
      "first_flagged": "2026-06-16",
      "reason": "Recovered"
    },
    "HONE": {
      "count": 0,
      "first_flagged": "2026-06-16",
      "reason": "Recovered"
    },
    "RENB": {
      "count": 0,
      "first_flagged": "2026-06-16",
      "reason": "Recovered"
    },
    "HES": {
      "count": 0,
      "first_flagged": "2026-06-16",
      "reason": "Recovered"
    },
    "MNMD": {
      "count": 0,
      "first_flagged": "2026-06-16",
      "reason": "Recovered"
    },
    "PX": {
      "count": 0,
      "first_flagged": "2026-06-16",
      "reason": "Recovered"
    },
    "PDCO": {
      "count": 0,
      "first_flagged": "2026-06-16",
      "reason": "Recovered"
    },
    "PCH": {
      "count": 0,
      "first_flagged": "2026-06-16",
      "reason": "Recovered"
    },
    "HMST": {
      "count": 0,
      "first_flagged": "2026-06-16",
      "reason": "Recovered"
    },
    "LANC": {
      "count": 0,
      "first_flagged": "2026-04-14",
      "reason": "Recovered"
    },
    "SWI": {
      "count": 0,
      "first_flagged": "2026-06-16",
      "reason": "Recovered"
    },
    "ZYXI": {
      "count": 0,
      "first_flagged": "2026-06-16",
      "reason": "Recovered"
    },
    "SAGE": {
      "count": 0,
      "first_flagged": "2026-06-16",
      "reason": "Recovered"
    },
    "SCS": {
      "count": 0,
      "first_flagged": "2026-06-16",
      "reason": "Recovered"
    },
    "WLLBW": {
      "count": 0,
      "first_flagged": "2026-06-16",
      "reason": "Recovered"
    },
    "PLYM": {
      "count": 0,
      "first_flagged": "2026-06-16",
      "reason": "Recovered"
    },
    "ITOS": {
      "count": 0,
      "first_flagged": "2026-06-16",
      "reason": "Recovered"
    },
    "DTC": {
      "count": 0,
      "first_flagged": "2026-06-16",
      "reason": "Recovered"
    },
    "ODP": {
      "count": 0,
      "first_flagged": "2026-06-16",
      "reason": "Recovered"
    },
    "MPX": {
      "count": 0,
      "first_flagged": "2026-06-16",
      "reason": "Recovered"
    },
    "DHIL": {
      "count": 0,
      "first_flagged": "2026-06-05",
      "reason": "Recovered"
    },
    "KFS": {
      "count": 0,
      "first_flagged": "2026-06-16",
      "reason": "Recovered"
    },
    "UHG": {
      "count": 0,
      "first_flagged": "2026-06-16",
      "reason": "Recovered"
    },
    "LNKB": {
      "count": 0,
      "first_flagged": "2026-06-16",
      "reason": "Recovered"
    },
    "EWCZ": {
      "count": 0,
      "first_flagged": "2026-06-16",
      "reason": "Recovered"
    },
    "CSGS": {
      "count": 0,
      "first_flagged": "2026-06-16",
      "reason": "Recovered"
    },
    "PKST": {
      "count": 0,
      "first_flagged": "2026-06-16",
      "reason": "Recovered"
    },
    "MEG": {
      "count": 0,
      "first_flagged": "2026-06-16",
      "reason": "Recovered"
    },
    "FIHL": {
      "count": 0,
      "first_flagged": "2026-06-16",
      "reason": "Recovered"
    },
    "GDEN": {
      "count": 0,
      "first_flagged": "2026-06-16",
      "reason": "Recovered"
    },
    "ASGN": {
      "count": 0,
      "first_flagged": "2026-06-16",
      "reason": "Recovered"
    },
    "EHAB": {
      "count": 0,
      "first_flagged": "2026-06-16",
      "reason": "Recovered"
    },
    "SNCY": {
      "count": 0,
      "first_flagged": "2026-06-16",
      "reason": "Recovered"
    },
    "EXPI": {
      "count": 0,
      "first_flagged": "2026-06-16",
      "reason": "Recovered"
    },
    "ACLX": {
      "count": 0,
      "first_flagged": "2026-03-25",
      "reason": "Recovered"
    },
    "STKL": {
      "count": 0,
      "first_flagged": "2026-06-16",
      "reason": "Recovered"
    },
    "VRE": {
      "count": 0,
      "first_flagged": "2026-06-16",
      "reason": "Recovered"
    },
    "CTLP": {
      "count": 0,
      "first_flagged": "2026-06-16",
      "reason": "Recovered"
    },
    "UDMY": {
      "count": 0,
      "first_flagged": "2026-06-16",
      "reason": "Recovered"
    },
    "SEMR": {
      "count": 0,
      "first_flagged": "2026-06-16",
      "reason": "Recovered"
    },
    "DAWN": {
      "count": 0,
      "first_flagged": "2026-06-16",
      "reason": "Recovered"
    },
    "FOLD": {
      "count": 0,
      "first_flagged": "2026-06-16",
      "reason": "Recovered"
    },
    "TPH": {
      "count": 0,
      "first_flagged": "2026-06-16",
      "reason": "Recovered"
    },
    "SLNO": {
      "count": 0,
      "first_flagged": "2026-06-16",
      "reason": "Recovered"
    },
    "BK": {
      "count": 0,
      "first_flagged": "2026-06-16",
      "reason": "Recovered"
    },
    "TERN": {
      "count": 0,
      "first_flagged": "2026-06-16",
      "reason": "Recovered"
    },
    "CTRA": {
      "count": 0,
      "first_flagged": "2026-06-16",
      "reason": "Recovered"
    },
    "NMRA": {
      "count": 0,
      "first_flagged": "2026-06-16",
      "reason": "Recovered"
    },
    "AKBA": {
      "count": 0,
      "first_flagged": "2026-06-05",
      "reason": "Recovered"
    },
    "CDLX": {
      "count": 0,
      "first_flagged": "2026-03-16",
      "reason": "Recovered"
    },
    "AHH": {
      "count": 0,
      "first_flagged": "2026-04-14",
      "reason": "Recovered"
    },
    "FMCC": {
      "count": 0,
      "first_flagged": "2026-04-16",
      "reason": "Recovered"
    },
    "GMGI": {
      "count": 0,
      "first_flagged": "2026-02-26",
      "reason": "Recovered"
    },
    "GMRE": {
      "count": 0,
      "first_flagged": "2026-04-14",
      "reason": "Recovered"
    },
    "ADDYY": {
      "count": 0,
      "first_flagged": "2026-04-16",
      "reason": "Recovered"
    },
    "AXL": {
      "count": 0,
      "first_flagged": "2026-04-14",
      "reason": "Recovered"
    },
    "FNMA": {
      "count": 0,
      "first_flagged": "2026-04-16",
      "reason": "Recovered"
    },
    "ATGE": {
      "count": 0,
      "first_flagged": "2026-04-14",
      "reason": "Recovered"
    },
    "HOWL": {
      "count": 0,
      "first_flagged": "2026-04-20",
      "reason": "Recovered"
    },
    "SKIN": {
      "count": 0,
      "first_flagged": "2026-04-20",
      "reason": "Recovered"
    },
    "WALD": {
      "count": 0,
      "first_flagged": "2026-04-22",
      "reason": "Recovered"
    },
    "DXLG": {
      "count": 0,
      "first_flagged": "2026-04-20",
      "reason": "Recovered"
    },
    "MYPS": {
      "count": 0,
      "first_flagged": "2026-04-20",
      "reason": "Recovered"
    },
    "BRCC": {
      "count": 0,
      "first_flagged": "2026-04-20",
      "reason": "Recovered"
    },
    "FSP": {
      "count": 0,
      "first_flagged": "2026-04-20",
      "reason": "Recovered"
    },
    "GETY": {
      "count": 0,
      "first_flagged": "2026-04-20",
      "reason": "Recovered"
    },
    "MXCT": {
      "count": 0,
      "first_flagged": "2026-04-20",
      "reason": "Recovered"
    },
    "GNS": {
      "count": 0,
      "first_flagged": "2026-04-20",
      "reason": "Recovered"
    },
    "HAIN": {
      "count": 0,
      "first_flagged": "2026-04-20",
      "reason": "Recovered"
    },
    "GUTS": {
      "count": 0,
      "first_flagged": "2026-04-20",
      "reason": "Recovered"
    },
    "HRTX": {
      "count": 0,
      "first_flagged": "2026-04-20",
      "reason": "Recovered"
    },
    "BLNK": {
      "count": 0,
      "first_flagged": "2026-04-20",
      "reason": "Recovered"
    },
    "DCGO": {
      "count": 0,
      "first_flagged": "2026-04-20",
      "reason": "Recovered"
    },
    "ARAY": {
      "count": 0,
      "first_flagged": "2026-04-20",
      "reason": "Recovered"
    },
    "CHGG": {
      "count": 0,
      "first_flagged": "2026-04-20",
      "reason": "Recovered"
    },
    "INVZ": {
      "count": 0,
      "first_flagged": "2026-04-20",
      "reason": "Recovered"
    },
    "LAB": {
      "count": 0,
      "first_flagged": "2026-04-20",
      "reason": "Recovered"
    },
    "MVIS": {
      "count": 0,
      "first_flagged": "2026-04-20",
      "reason": "Recovered"
    },
    "MAPS": {
      "count": 0,
      "first_flagged": "2026-04-20",
      "reason": "Recovered"
    },
    "ALIT": {
      "count": 0,
      "first_flagged": "2026-04-20",
      "reason": "Recovered"
    },
    "BYND": {
      "count": 0,
      "first_flagged": "2026-04-20",
      "reason": "Recovered"
    },
    "GAME": {
      "count": 0,
      "first_flagged": "2026-04-20",
      "reason": "Recovered"
    },
    "MTAL": {
      "count": 0,
      "first_flagged": "2026-04-08",
      "reason": "Recovered"
    },
    "LYRA": {
      "count": 0,
      "first_flagged": "2026-04-13",
      "reason": "Recovered"
    },
    "HCAT": {
      "count": 0,
      "first_flagged": "2026-04-13",
      "reason": "Recovered"
    },
    "RXT": {
      "count": 0,
      "first_flagged": "2026-04-10",
      "reason": "Recovered"
    },
    "DXD": {
      "count": 0,
      "first_flagged": "2026-04-08",
      "reason": "Recovered"
    },
    "SDY": {
      "count": 0,
      "first_flagged": "2026-04-08",
      "reason": "Recovered"
    },
    "VUG": {
      "count": 0,
      "first_flagged": "2026-04-08",
      "reason": "Recovered"
    },
    "DVY": {
      "count": 0,
      "first_flagged": "2026-04-08",
      "reason": "Recovered"
    },
    "RWR": {
      "count": 0,
      "first_flagged": "2026-04-08",
      "reason": "Recovered"
    },
    "IGV": {
      "count": 0,
      "first_flagged": "2026-04-08",
      "reason": "Recovered"
    },
    "USRT": {
      "count": 0,
      "first_flagged": "2026-04-08",
      "reason": "Recovered"
    },
    "ACWI": {
      "count": 0,
      "first_flagged": "2026-04-08",
      "reason": "Recovered"
    },
    "CLOU": {
      "count": 0,
      "first_flagged": "2026-04-08",
      "reason": "Recovered"
    },
    "REZ": {
      "count": 0,
      "first_flagged": "2026-04-08",
      "reason": "Recovered"
    },
    "VGT": {
      "count": 0,
      "first_flagged": "2026-04-08",
      "reason": "Recovered"
    },
    "VEU": {
      "count": 0,
      "first_flagged": "2026-04-08",
      "reason": "Recovered"
    },
    "SPHD": {
      "count": 0,
      "first_flagged": "2026-04-08",
      "reason": "Recovered"
    },
    "VTEB": {
      "count": 0,
      "first_flagged": "2026-04-08",
      "reason": "Recovered"
    },
    "SOYB": {
      "count": 0,
      "first_flagged": "2026-04-08",
      "reason": "Recovered"
    },
    "WCLD": {
      "count": 0,
      "first_flagged": "2026-04-08",
      "reason": "Recovered"
    },
    "EWU": {
      "count": 0,
      "first_flagged": "2026-04-08",
      "reason": "Recovered"
    },
    "IWD": {
      "count": 0,
      "first_flagged": "2026-04-08",
      "reason": "Recovered"
    },
    "VBR": {
      "count": 0,
      "first_flagged": "2026-04-08",
      "reason": "Recovered"
    },
    "PDBC": {
      "count": 0,
      "first_flagged": "2026-04-08",
      "reason": "Recovered"
    },
    "SHY": {
      "count": 0,
      "first_flagged": "2026-04-08",
      "reason": "Recovered"
    },
    "CORN": {
      "count": 0,
      "first_flagged": "2026-04-08",
      "reason": "Recovered"
    },
    "UVXY": {
      "count": 0,
      "first_flagged": "2026-04-08",
      "reason": "Recovered"
    },
    "REM": {
      "count": 0,
      "first_flagged": "2026-04-08",
      "reason": "Recovered"
    },
    "DBC": {
      "count": 0,
      "first_flagged": "2026-04-08",
      "reason": "Recovered"
    },
    "VO": {
      "count": 0,
      "first_flagged": "2026-04-08",
      "reason": "Recovered"
    },
    "HACK": {
      "count": 0,
      "first_flagged": "2026-04-08",
      "reason": "Recovered"
    },
    "SCHH": {
      "count": 0,
      "first_flagged": "2026-04-08",
      "reason": "Recovered"
    },
    "EFA": {
      "count": 0,
      "first_flagged": "2026-04-08",
      "reason": "Recovered"
    },
    "AGG": {
      "count": 0,
      "first_flagged": "2026-04-08",
      "reason": "Recovered"
    },
    "EWG": {
      "count": 0,
      "first_flagged": "2026-04-08",
      "reason": "Recovered"
    },
    "IJR": {
      "count": 0,
      "first_flagged": "2026-04-08",
      "reason": "Recovered"
    },
    "SOXX": {
      "count": 0,
      "first_flagged": "2026-04-08",
      "reason": "Recovered"
    },
    "VIG": {
      "count": 0,
      "first_flagged": "2026-04-08",
      "reason": "Recovered"
    },
    "WEAT": {
      "count": 0,
      "first_flagged": "2026-04-08",
      "reason": "Recovered"
    },
    "DGRO": {
      "count": 0,
      "first_flagged": "2026-04-08",
      "reason": "Recovered"
    },
    "VTV": {
      "count": 0,
      "first_flagged": "2026-04-08",
      "reason": "Recovered"
    },
    "EWJ": {
      "count": 0,
      "first_flagged": "2026-04-08",
      "reason": "Recovered"
    },
    "DBA": {
      "count": 0,
      "first_flagged": "2026-04-08",
      "reason": "Recovered"
    },
    "ARKQ": {
      "count": 0,
      "first_flagged": "2026-04-08",
      "reason": "Recovered"
    },
    "JNK": {
      "count": 0,
      "first_flagged": "2026-04-08",
      "reason": "Recovered"
    },
    "VWO": {
      "count": 0,
      "first_flagged": "2026-04-08",
      "reason": "Recovered"
    },
    "BND": {
      "count": 0,
      "first_flagged": "2026-04-08",
      "reason": "Recovered"
    },
    "PSQ": {
      "count": 0,
      "first_flagged": "2026-04-08",
      "reason": "Recovered"
    },
    "IJH": {
      "count": 0,
      "first_flagged": "2026-04-08",
      "reason": "Recovered"
    },
    "NOBL": {
      "count": 0,
      "first_flagged": "2026-04-08",
      "reason": "Recovered"
    },
    "DOG": {
      "count": 0,
      "first_flagged": "2026-04-08",
      "reason": "Recovered"
    },
    "RWM": {
      "count": 0,
      "first_flagged": "2026-04-08",
      "reason": "Recovered"
    },
    "FREL": {
      "count": 0,
      "first_flagged": "2026-04-08",
      "reason": "Recovered"
    },
    "TWM": {
      "count": 0,
      "first_flagged": "2026-04-08",
      "reason": "Recovered"
    },
    "IXUS": {
      "count": 0,
      "first_flagged": "2026-04-08",
      "reason": "Recovered"
    },
    "VNQI": {
      "count": 0,
      "first_flagged": "2026-04-08",
      "reason": "Recovered"
    },
    "VBK": {
      "count": 0,
      "first_flagged": "2026-04-08",
      "reason": "Recovered"
    },
    "IWF": {
      "count": 0,
      "first_flagged": "2026-04-08",
      "reason": "Recovered"
    },
    "SH": {
      "count": 0,
      "first_flagged": "2026-04-08",
      "reason": "Recovered"
    },
    "VNQ": {
      "count": 0,
      "first_flagged": "2026-04-08",
      "reason": "Recovered"
    },
    "FTEC": {
      "count": 0,
      "first_flagged": "2026-04-08",
      "reason": "Recovered"
    },
    "HDV": {
      "count": 0,
      "first_flagged": "2026-04-08",
      "reason": "Recovered"
    },
    "JELD": {
      "count": 0,
      "first_flagged": "2026-04-08",
      "reason": "Recovered"
    },
    "BKNG": {
      "count": 0,
      "first_flagged": "2026-04-06",
      "reason": "Recovered"
    },
    "ATNM": {
      "count": 0,
      "first_flagged": "2026-04-02",
      "reason": "Recovered"
    },
    "AGL": {
      "count": 0,
      "first_flagged": "2026-03-30",
      "reason": "Recovered"
    },
    "BARK": {
      "count": 0,
      "first_flagged": "2026-03-30",
      "reason": "Recovered"
    },
    "NDSN": {
      "count": 0,
      "first_flagged": "2026-03-25",
      "reason": "Recovered"
    },
    "NET": {
      "count": 0,
      "first_flagged": "2026-03-25",
      "reason": "Recovered"
    },
    "NDAQ": {
      "count": 0,
      "first_flagged": "2026-03-25",
      "reason": "Recovered"
    },
    "NEM": {
      "count": 0,
      "first_flagged": "2026-03-25",
      "reason": "Recovered"
    },
    "NEE": {
      "count": 0,
      "first_flagged": "2026-03-25",
      "reason": "Recovered"
    },
    "LESL": {
      "count": 0,
      "first_flagged": "2026-03-03",
      "reason": "Recovered"
    },
    "AMC": {
      "count": 0,
      "first_flagged": "2026-03-30",
      "reason": "Recovered"
    },
    "ALXO": {
      "count": 0,
      "first_flagged": "2026-03-31",
      "reason": "Recovered"
    },
    "CSTE": {
      "count": 0,
      "first_flagged": "2026-03-16",
      "reason": "Recovered"
    },
    "ATEN": {
      "count": 0,
      "first_flagged": "2026-03-26",
      "reason": "Recovered"
    },
    "ABNB": {
      "count": 0,
      "first_flagged": "2026-03-26",
      "reason": "Recovered"
    },
    "CCO": {
      "count": 0,
      "first_flagged": "2026-03-26",
      "reason": "Recovered"
    },
    "GDX": {
      "count": 0,
      "first_flagged": "2026-03-26",
      "reason": "Recovered"
    },
    "AAPL": {
      "count": 0,
      "first_flagged": "2026-03-23",
      "reason": "Recovered"
    },
    "AVGO": {
      "count": 0,
      "first_flagged": "2026-03-16",
      "reason": "Recovered"
    },
    "BRO": {
      "count": 0,
      "first_flagged": "2026-03-23",
      "reason": "Recovered"
    },
    "AXP": {
      "count": 0,
      "first_flagged": "2026-03-23",
      "reason": "Recovered"
    },
    "AEP": {
      "count": 0,
      "first_flagged": "2026-03-25",
      "reason": "Recovered"
    },
    "AFRM": {
      "count": 0,
      "first_flagged": "2026-03-25",
      "reason": "Recovered"
    },
    "BSX": {
      "count": 0,
      "first_flagged": "2026-03-23",
      "reason": "Recovered"
    },
    "AAOI": {
      "count": 0,
      "first_flagged": "2026-03-16",
      "reason": "Recovered"
    },
    "DKNG": {
      "count": 0,
      "first_flagged": "2026-03-23",
      "reason": "Recovered"
    },
    "NCLH": {
      "count": 0,
      "first_flagged": "2026-03-25",
      "reason": "Recovered"
    },
    "SMXT": {
      "count": 0,
      "first_flagged": "2026-03-16",
      "reason": "Recovered"
    },
    "SURG": {
      "count": 0,
      "first_flagged": "2026-03-16",
      "reason": "Recovered"
    },
    "PRPL": {
      "count": 0,
      "first_flagged": "2026-03-16",
      "reason": "Recovered"
    },
    "TMRC": {
      "count": 0,
      "first_flagged": "2026-03-16",
      "reason": "Recovered"
    },
    "NOTE": {
      "count": 0,
      "first_flagged": "2026-03-16",
      "reason": "Recovered"
    },
    "NRDY": {
      "count": 0,
      "first_flagged": "2026-03-16",
      "reason": "Recovered"
    },
    "OPAD": {
      "count": 0,
      "first_flagged": "2026-03-16",
      "reason": "Recovered"
    },
    "OTLK": {
      "count": 0,
      "first_flagged": "2026-03-16",
      "reason": "Recovered"
    },
    "UP": {
      "count": 0,
      "first_flagged": "2026-03-16",
      "reason": "Recovered"
    },
    "SLQT": {
      "count": 0,
      "first_flagged": "2026-03-16",
      "reason": "Recovered"
    },
    "REKR": {
      "count": 0,
      "first_flagged": "2026-02-26",
      "reason": "Recovered"
    },
    "SKYE": {
      "count": 0,
      "first_flagged": "2026-03-16",
      "reason": "Recovered"
    },
    "TNYA": {
      "count": 0,
      "first_flagged": "2026-03-16",
      "reason": "Recovered"
    },
    "ZSPC": {
      "count": 0,
      "first_flagged": "2026-03-16",
      "reason": "Recovered"
    },
    "ARKO": {
      "count": 0,
      "first_flagged": "2026-03-24",
      "reason": "Recovered"
    },
    "ABAT": {
      "count": 0,
      "first_flagged": "2026-03-24",
      "reason": "Recovered"
    },
    "AAL": {
      "count": 0,
      "first_flagged": "2026-03-24",
      "reason": "Recovered"
    },
    "AG": {
      "count": 0,
      "first_flagged": "2026-03-23",
      "reason": "Recovered"
    },
    "CAH": {
      "count": 0,
      "first_flagged": "2026-03-18",
      "reason": "Recovered"
    },
    "CME": {
      "count": 0,
      "first_flagged": "2026-03-18",
      "reason": "Recovered"
    },
    "CRDO": {
      "count": 0,
      "first_flagged": "2026-03-18",
      "reason": "Recovered"
    },
    "COP": {
      "count": 0,
      "first_flagged": "2026-03-18",
      "reason": "Recovered"
    },
    "C": {
      "count": 0,
      "first_flagged": "2026-03-18",
      "reason": "Recovered"
    },
    "CAG": {
      "count": 0,
      "first_flagged": "2026-03-16",
      "reason": "Recovered"
    },
    "F": {
      "count": 0,
      "first_flagged": "2026-03-18",
      "reason": "Recovered"
    },
    "COOK": {
      "count": 0,
      "first_flagged": "2026-03-16",
      "reason": "Recovered"
    },
    "CMCO": {
      "count": 0,
      "first_flagged": "2026-03-16",
      "reason": "Recovered"
    },
    "ADEA": {
      "count": 0,
      "first_flagged": "2026-03-16",
      "reason": "Recovered"
    },
    "APD": {
      "count": 0,
      "first_flagged": "2026-03-16",
      "reason": "Recovered"
    },
    "AVPT": {
      "count": 0,
      "first_flagged": "2026-03-16",
      "reason": "Recovered"
    },
    "COIN": {
      "count": 0,
      "first_flagged": "2026-03-16",
      "reason": "Recovered"
    },
    "CMG": {
      "count": 0,
      "first_flagged": "2026-03-16",
      "reason": "Recovered"
    },
    "EVCM": {
      "count": 0,
      "first_flagged": "2026-03-16",
      "reason": "Recovered"
    },
    "CRL": {
      "count": 0,
      "first_flagged": "2026-03-16",
      "reason": "Recovered"
    },
    "EPAM": {
      "count": 0,
      "first_flagged": "2026-03-16",
      "reason": "Recovered"
    },
    "CHD": {
      "count": 0,
      "first_flagged": "2026-03-16",
      "reason": "Recovered"
    },
    "GTLS": {
      "count": 0,
      "first_flagged": "2026-03-16",
      "reason": "Recovered"
    },
    "GIS": {
      "count": 0,
      "first_flagged": "2026-03-16",
      "reason": "Recovered"
    },
    "HIMS": {
      "count": 0,
      "first_flagged": "2026-03-16",
      "reason": "Recovered"
    },
    "HBIO": {
      "count": 0,
      "first_flagged": "2026-03-16",
      "reason": "Recovered"
    },
    "SABR": {
      "count": 0,
      "first_flagged": "2026-02-26",
      "reason": "Recovered"
    }
  }
}