{
  "sync_time": "2026-02-27T13:35:01.628187",
  "reports_synced": 8,
  "reports": [
    {
      "scanner": "Institutional Scanner",
      "file": "institutional_latest.html",
      "timestamp": "2026-02-27T11:02:41.476132",
      "source": "/home/j/Desktop/Trading Scans/daily/institutional/INST_SCAN_2026-02-27.html",
      "size_kb": 35.8
    },
    {
      "scanner": "Enhanced Breakout",
      "file": "enhanced_latest.html",
      "timestamp": "2026-02-27T13:31:31.037283",
      "source": "/home/j/Desktop/Trading Scans/daily/enhanced/BREAKOUT_SCAN_2026-02-27.html",
      "size_kb": 40.3
    },
    {
      "scanner": "V3 Compression",
      "file": "v3_compression_latest.html",
      "timestamp": "2026-02-27T13:32:21.176887",
      "source": "/home/j/Desktop/Trading Scans/daily/v3_compression/RANGE_COMPRESSION_V3_2026-02-27.html",
      "size_kb": 41.1
    },
    {
      "scanner": "ETF Scanner",
      "file": "etf_latest.html",
      "timestamp": "2026-02-26T16:03:50.296998",
      "source": "/home/j/Desktop/Trading Scans/etf/etf_scan_20260226_1603.html",
      "size_kb": 14.2
    },
    {
      "scanner": "Mega Under-$50",
      "file": "under50_latest.html",
      "timestamp": "2026-02-26T16:03:51.184157",
      "source": "/home/j/Desktop/Trading Scans/mega_under50/mega_under50_scan_20260226_1603.html",
      "size_kb": 16.5
    },
    {
      "scanner": "Cross-Scanner Intelligence",
      "file": "cross_scanner_latest.html",
      "timestamp": "2026-02-27T01:01:43.164851",
      "source": "/home/j/Desktop/Trading Scans/cross_scanner/cross_scanner_latest.html",
      "size_kb": 219.4
    },
    {
      "scanner": "Setup Scanner",
      "file": "setups_latest.html",
      "timestamp": "2026-02-27T13:32:26.550198",
      "source": "/home/j/Desktop/Trading Scans/daily/setups/SETUP_SCAN_2026-02-27.html",
      "size_kb": 43.5
    },
    {
      "scanner": "Unified Multi-Day",
      "file": "unified_latest.html",
      "timestamp": "2026-02-27T13:33:08.684894",
      "source": "/home/j/Desktop/Trading Scans/daily/unified/UNIFIED_SCAN_2026-02-27.html",
      "size_kb": 35.1
    }
  ]
}