[{"symbol": "ANIK", "score": 120, "price": 12.79, "stop": 0.0, "target": 0.0, "signals": "OBV RISING \u2022 EMA BULLISH \u2022 STRONG ACCUM \u2022 STEADY VOL \u2022 ACTIVE \u2022 FULL SUPPORT \u2022 NEAR 20D HIGH \u2022 UPPER RANGE \u2022 MOMENTUM", "scanner": "institutional"}, {"symbol": "CABA", "score": 120, "price": 3.72, "stop": 0.0, "target": 0.0, "signals": "OBV RISING \u2022 EMA BULLISH \u2022 STRONG ACCUM \u2022 STEADY VOL \u2022 ACTIVE \u2022 FULL SUPPORT \u2022 NEAR 20D HIGH \u2022 UPPER RANGE \u2022 MOMENTUM", "scanner": "institutional"}, {"symbol": "CLYM", "score": 120, "price": 6.97, "stop": 0.0, "target": 0.0, "signals": "OBV RISING \u2022 EMA BULLISH \u2022 STRONG ACCUM \u2022 STEADY VOL \u2022 ACTIVE \u2022 FULL SUPPORT \u2022 NEAR 20D HIGH \u2022 UPPER RANGE \u2022 MOMENTUM", "scanner": "institutional"}, {"symbol": "CRBU", "score": 120, "price": 2.01, "stop": 0.0, "target": 0.0, "signals": "OBV RISING \u2022 EMA BULLISH \u2022 STRONG ACCUM \u2022 STEADY VOL \u2022 ACTIVE \u2022 FULL SUPPORT \u2022 NEAR 20D HIGH \u2022 UPPER RANGE \u2022 MOMENTUM", "scanner": "institutional"}, {"symbol": "HLX", "score": 120, "price": 9.62, "stop": 0.0, "target": 0.0, "signals": "OBV RISING \u2022 EMA BULLISH \u2022 STRONG ACCUM \u2022 STEADY VOL \u2022 ACTIVE \u2022 FULL SUPPORT \u2022 NEAR 20D HIGH \u2022 UPPER RANGE \u2022 MOMENTUM", "scanner": "institutional"}, {"symbol": "CBUS", "score": 100, "price": 3.68, "stop": 3.03, "target": 4.67, "signals": "NR7 TIGHT \u2022 NORMAL VOL \u2022 BULL TREND \u2022 UPPER RANGE \u2022 NEAR HIGHS \u2022 GAP \u2022 LIQUID", "scanner": "v3_compression"}, {"symbol": "CSTM", "score": 100, "price": 25.81, "stop": 22.97, "target": 30.07, "signals": "NR7 TIGHT \u2022 NORMAL VOL \u2022 BULL TREND \u2022 UPPER RANGE \u2022 NEAR HIGHS \u2022 GAP \u2022 LIQUID", "scanner": "v3_compression"}, {"symbol": "CTRN", "score": 100, "price": 46.17, "stop": 41.7, "target": 52.88, "signals": "NR7 TIGHT \u2022 NORMAL VOL \u2022 BULL TREND \u2022 UPPER RANGE \u2022 NEAR HIGHS \u2022 GAP \u2022 LIQUID", "scanner": "v3_compression"}, {"symbol": "EEM", "score": 100, "price": 63.38, "stop": 61.48, "target": 66.23, "signals": "NR7 TIGHT \u2022 NORMAL VOL \u2022 BULL TREND \u2022 UPPER RANGE \u2022 NEAR HIGHS \u2022 GAP \u2022 LIQUID", "scanner": "v3_compression"}, {"symbol": "IAG", "score": 100, "price": 22.97, "stop": 20.22, "target": 27.08, "signals": "NR7 TIGHT \u2022 NORMAL VOL \u2022 BULL TREND \u2022 UPPER RANGE \u2022 NEAR HIGHS \u2022 GAP \u2022 LIQUID", "scanner": "v3_compression"}]